<?xml version="1.0" encoding="UTF-8"?>
<!DOCTYPE mapper PUBLIC "-//mybatis.org//DTD Mapper 3.0//EN" "http://mybatis.org/dtd/mybatis-3-mapper.dtd">
<mapper namespace="com.guo.springboot.dao.ProfileMapper">
  <resultMap id="BaseResultMap" type="com.guo.springboot.domain.Profile">
    <!--
      WARNING - @mbggenerated
      This element is automatically generated by MyBatis Generator, do not modify.
      This element was generated on Thu Apr 12 19:37:39 CST 2018.
    -->
    <id column="PP_id" jdbcType="INTEGER" property="id" />
    <result column="PP_username" jdbcType="VARCHAR" property="username" />
    <result column="PP_password" jdbcType="VARCHAR" property="password" />
    <result column="PP_mobile" jdbcType="VARCHAR" property="mobile" />
    <result column="PP_address" jdbcType="VARCHAR" property="address" />
    <result column="PP_update_by" jdbcType="INTEGER" property="updateBy" />
    <result column="PP_update_time" jdbcType="TIMESTAMP" property="updateTime" />
    <result column="PP_created_time" jdbcType="TIMESTAMP" property="createdTime" />
    <result column="PP_created_by" jdbcType="INTEGER" property="createdBy" />
  </resultMap>
  <sql id="Example_Where_Clause">
    <!--
      WARNING - @mbggenerated
      This element is automatically generated by MyBatis Generator, do not modify.
      This element was generated on Thu Apr 12 19:37:39 CST 2018.
    -->
    <where>
      <foreach collection="oredCriteria" item="criteria" separator="or">
        <if test="criteria.valid">
          <trim prefix="(" prefixOverrides="and" suffix=")">
            <foreach collection="criteria.criteria" item="criterion">
              <choose>
                <when test="criterion.noValue">
                  and ${criterion.condition}
                </when>
                <when test="criterion.singleValue">
                  and ${criterion.condition} #{criterion.value}
                </when>
                <when test="criterion.betweenValue">
                  and ${criterion.condition} #{criterion.value} and #{criterion.secondValue}
                </when>
                <when test="criterion.listValue">
                  and ${criterion.condition}
                  <foreach close=")" collection="criterion.value" item="listItem" open="(" separator=",">
                    #{listItem}
                  </foreach>
                </when>
              </choose>
            </foreach>
          </trim>
        </if>
      </foreach>
    </where>
  </sql>
  <sql id="Update_By_Example_Where_Clause">
    <!--
      WARNING - @mbggenerated
      This element is automatically generated by MyBatis Generator, do not modify.
      This element was generated on Thu Apr 12 19:37:39 CST 2018.
    -->
    <where>
      <foreach collection="example.oredCriteria" item="criteria" separator="or">
        <if test="criteria.valid">
          <trim prefix="(" prefixOverrides="and" suffix=")">
            <foreach collection="criteria.criteria" item="criterion">
              <choose>
                <when test="criterion.noValue">
                  and ${criterion.condition}
                </when>
                <when test="criterion.singleValue">
                  and ${criterion.condition} #{criterion.value}
                </when>
                <when test="criterion.betweenValue">
                  and ${criterion.condition} #{criterion.value} and #{criterion.secondValue}
                </when>
                <when test="criterion.listValue">
                  and ${criterion.condition}
                  <foreach close=")" collection="criterion.value" item="listItem" open="(" separator=",">
                    #{listItem}
                  </foreach>
                </when>
              </choose>
            </foreach>
          </trim>
        </if>
      </foreach>
    </where>
  </sql>
  <sql id="Base_Column_List">
    <!--
      WARNING - @mbggenerated
      This element is automatically generated by MyBatis Generator, do not modify.
      This element was generated on Thu Apr 12 19:37:39 CST 2018.
    -->
    PP.id as PP_id, PP.username as PP_username, PP.password as PP_password, PP.mobile as PP_mobile, 
    PP.address as PP_address, PP.update_by as PP_update_by, PP.update_time as PP_update_time, 
    PP.created_time as PP_created_time, PP.created_by as PP_created_by
  </sql>
  <select id="selectByExample" parameterType="com.guo.springboot.domain.ProfileExample" resultMap="BaseResultMap">
    <!--
      WARNING - @mbggenerated
      This element is automatically generated by MyBatis Generator, do not modify.
      This element was generated on Thu Apr 12 19:37:39 CST 2018.
    -->
    select
    <if test="distinct">
      distinct
    </if>
    <include refid="Base_Column_List" />
    from profile PP
    <if test="_parameter != null">
      <include refid="Example_Where_Clause" />
    </if>
    <if test="orderByClause != null">
      order by ${orderByClause}
    </if>
  </select>
  <select id="selectByPrimaryKey" parameterType="java.lang.Integer" resultMap="BaseResultMap">
    <!--
      WARNING - @mbggenerated
      This element is automatically generated by MyBatis Generator, do not modify.
      This element was generated on Thu Apr 12 19:37:39 CST 2018.
    -->
    select 
    <include refid="Base_Column_List" />
    from profile PP
    where PP.id = #{id,jdbcType=INTEGER}
  </select>
  <delete id="deleteByPrimaryKey" parameterType="java.lang.Integer">
    <!--
      WARNING - @mbggenerated
      This element is automatically generated by MyBatis Generator, do not modify.
      This element was generated on Thu Apr 12 19:37:39 CST 2018.
    -->
    delete from profile
    where id = #{id,jdbcType=INTEGER}
  </delete>
  <delete id="deleteByExample" parameterType="com.guo.springboot.domain.ProfileExample">
    <!--
      WARNING - @mbggenerated
      This element is automatically generated by MyBatis Generator, do not modify.
      This element was generated on Thu Apr 12 19:37:39 CST 2018.
    -->
    delete from profile PP
    <if test="_parameter != null">
      <include refid="Example_Where_Clause" />
    </if>
  </delete>
  <insert id="insert" parameterType="com.guo.springboot.domain.Profile">
    <!--
      WARNING - @mbggenerated
      This element is automatically generated by MyBatis Generator, do not modify.
      This element was generated on Thu Apr 12 19:37:39 CST 2018.
    -->
    insert into profile (id, username, password, 
      mobile, address, update_by, 
      update_time, created_time, created_by
      )
    values (#{id,jdbcType=INTEGER}, #{username,jdbcType=VARCHAR}, #{password,jdbcType=VARCHAR}, 
      #{mobile,jdbcType=VARCHAR}, #{address,jdbcType=VARCHAR}, #{updateBy,jdbcType=INTEGER}, 
      #{updateTime,jdbcType=TIMESTAMP}, #{createdTime,jdbcType=TIMESTAMP}, #{createdBy,jdbcType=INTEGER}
      )
  </insert>
  <insert id="insertSelective" parameterType="com.guo.springboot.domain.Profile">
    <!--
      WARNING - @mbggenerated
      This element is automatically generated by MyBatis Generator, do not modify.
      This element was generated on Thu Apr 12 19:37:39 CST 2018.
    -->
    insert into profile
    <trim prefix="(" suffix=")" suffixOverrides=",">
      <if test="id != null">
        id,
      </if>
      <if test="username != null">
        username,
      </if>
      <if test="password != null">
        password,
      </if>
      <if test="mobile != null">
        mobile,
      </if>
      <if test="address != null">
        address,
      </if>
      <if test="updateBy != null">
        update_by,
      </if>
      <if test="updateTime != null">
        update_time,
      </if>
      <if test="createdTime != null">
        created_time,
      </if>
      <if test="createdBy != null">
        created_by,
      </if>
    </trim>
    <trim prefix="values (" suffix=")" suffixOverrides=",">
      <if test="id != null">
        #{id,jdbcType=INTEGER},
      </if>
      <if test="username != null">
        #{username,jdbcType=VARCHAR},
      </if>
      <if test="password != null">
        #{password,jdbcType=VARCHAR},
      </if>
      <if test="mobile != null">
        #{mobile,jdbcType=VARCHAR},
      </if>
      <if test="address != null">
        #{address,jdbcType=VARCHAR},
      </if>
      <if test="updateBy != null">
        #{updateBy,jdbcType=INTEGER},
      </if>
      <if test="updateTime != null">
        #{updateTime,jdbcType=TIMESTAMP},
      </if>
      <if test="createdTime != null">
        #{createdTime,jdbcType=TIMESTAMP},
      </if>
      <if test="createdBy != null">
        #{createdBy,jdbcType=INTEGER},
      </if>
    </trim>
  </insert>
  <select id="countByExample" parameterType="com.guo.springboot.domain.ProfileExample" resultType="java.lang.Integer">
    <!--
      WARNING - @mbggenerated
      This element is automatically generated by MyBatis Generator, do not modify.
      This element was generated on Thu Apr 12 19:37:39 CST 2018.
    -->
    select count(*) from profile PP
    <if test="_parameter != null">
      <include refid="Example_Where_Clause" />
    </if>
  </select>
  <update id="updateByExampleSelective" parameterType="map">
    <!--
      WARNING - @mbggenerated
      This element is automatically generated by MyBatis Generator, do not modify.
      This element was generated on Thu Apr 12 19:37:39 CST 2018.
    -->
    update profile PP
    <set>
      <if test="record.id != null">
        PP.id = #{record.id,jdbcType=INTEGER},
      </if>
      <if test="record.username != null">
        PP.username = #{record.username,jdbcType=VARCHAR},
      </if>
      <if test="record.password != null">
        PP.password = #{record.password,jdbcType=VARCHAR},
      </if>
      <if test="record.mobile != null">
        PP.mobile = #{record.mobile,jdbcType=VARCHAR},
      </if>
      <if test="record.address != null">
        PP.address = #{record.address,jdbcType=VARCHAR},
      </if>
      <if test="record.updateBy != null">
        PP.update_by = #{record.updateBy,jdbcType=INTEGER},
      </if>
      <if test="record.updateTime != null">
        PP.update_time = #{record.updateTime,jdbcType=TIMESTAMP},
      </if>
      <if test="record.createdTime != null">
        PP.created_time = #{record.createdTime,jdbcType=TIMESTAMP},
      </if>
      <if test="record.createdBy != null">
        PP.created_by = #{record.createdBy,jdbcType=INTEGER},
      </if>
    </set>
    <if test="_parameter != null">
      <include refid="Update_By_Example_Where_Clause" />
    </if>
  </update>
  <update id="updateByExample" parameterType="map">
    <!--
      WARNING - @mbggenerated
      This element is automatically generated by MyBatis Generator, do not modify.
      This element was generated on Thu Apr 12 19:37:39 CST 2018.
    -->
    update profile PP
    set PP.id = #{record.id,jdbcType=INTEGER},
      PP.username = #{record.username,jdbcType=VARCHAR},
      PP.password = #{record.password,jdbcType=VARCHAR},
      PP.mobile = #{record.mobile,jdbcType=VARCHAR},
      PP.address = #{record.address,jdbcType=VARCHAR},
      PP.update_by = #{record.updateBy,jdbcType=INTEGER},
      PP.update_time = #{record.updateTime,jdbcType=TIMESTAMP},
      PP.created_time = #{record.createdTime,jdbcType=TIMESTAMP},
      PP.created_by = #{record.createdBy,jdbcType=INTEGER}
    <if test="_parameter != null">
      <include refid="Update_By_Example_Where_Clause" />
    </if>
  </update>
  <update id="updateByPrimaryKeySelective" parameterType="com.guo.springboot.domain.Profile">
    <!--
      WARNING - @mbggenerated
      This element is automatically generated by MyBatis Generator, do not modify.
      This element was generated on Thu Apr 12 19:37:39 CST 2018.
    -->
    update profile
    <set>
      <if test="username != null">
        username = #{username,jdbcType=VARCHAR},
      </if>
      <if test="password != null">
        password = #{password,jdbcType=VARCHAR},
      </if>
      <if test="mobile != null">
        mobile = #{mobile,jdbcType=VARCHAR},
      </if>
      <if test="address != null">
        address = #{address,jdbcType=VARCHAR},
      </if>
      <if test="updateBy != null">
        update_by = #{updateBy,jdbcType=INTEGER},
      </if>
      <if test="updateTime != null">
        update_time = #{updateTime,jdbcType=TIMESTAMP},
      </if>
      <if test="createdTime != null">
        created_time = #{createdTime,jdbcType=TIMESTAMP},
      </if>
      <if test="createdBy != null">
        created_by = #{createdBy,jdbcType=INTEGER},
      </if>
    </set>
    where id = #{id,jdbcType=INTEGER}
  </update>
  <update id="updateByPrimaryKey" parameterType="com.guo.springboot.domain.Profile">
    <!--
      WARNING - @mbggenerated
      This element is automatically generated by MyBatis Generator, do not modify.
      This element was generated on Thu Apr 12 19:37:39 CST 2018.
    -->
    update profile
    set username = #{username,jdbcType=VARCHAR},
      password = #{password,jdbcType=VARCHAR},
      mobile = #{mobile,jdbcType=VARCHAR},
      address = #{address,jdbcType=VARCHAR},
      update_by = #{updateBy,jdbcType=INTEGER},
      update_time = #{updateTime,jdbcType=TIMESTAMP},
      created_time = #{createdTime,jdbcType=TIMESTAMP},
      created_by = #{createdBy,jdbcType=INTEGER}
    where id = #{id,jdbcType=INTEGER}
  </update>
</mapper>